polyjuice/__init__.py
polyjuice/errors.py
polyjuice/fields.py
polyjuice/options.py
polyjuice/related_fields.py
polyjuice-0.1.0.dist-info/WHEEL
polyjuice-0.1.0.dist-info/METADATA
polyjuice-0.1.0.dist-info/RECORD
