Metadata-Version: 2.1
Name: polyjuice
Version: 0.1.0
Summary: SQLAlchemy tables disguised as Django models.
Home-page: https://github.com/ducdetronquito/polyjuice
Keywords: Django,SQLAlchemy
Author: ducdetronquito
Author-email: guillaume.paulet@giome.fr
Requires-Python: >=3.6,<4.0
Classifier: Programming Language :: Python :: 3
Classifier: Programming Language :: Python :: 3.6
Classifier: Programming Language :: Python :: 3.7
Classifier: Programming Language :: Python :: 3.8
Requires-Dist: django (>=2.2.0,<2.3.0)
Requires-Dist: sqlalchemy (>=1.3.0,<1.4.0)
Project-URL: Repository, https://github.com/ducdetronquito/polyjuice
